qPyUtils/__init__.py
qPyUtils/constant.py
qPyUtils/parallel.py
qPyUtils/streaming.py
qPyUtils/text.py
qPyUtils/web.py
qPyUtils/debug/__init__.py
qPyUtils/log/__init__.py
qPyUtils/log/timer.py
qPyUtils/log/writer.py
qPyUtils/log/parser/__init__.py
qPyUtils/log/parser/base.py
qPyUtils/log/parser/sn_log.py
qPyUtils/log/parser/sn_vali.py
qPyUtils/log/parser/ts_log.py
qPyUtils/system/__init__.py
qPyUtils/system/file_system.py
qPyUtils/system/portforward.py
qPyUtils-0.1.9.data/scripts/portforward
qPyUtils-0.1.9.dist-info/METADATA
qPyUtils-0.1.9.dist-info/WHEEL
qPyUtils-0.1.9.dist-info/namespace_packages.txt
qPyUtils-0.1.9.dist-info/top_level.txt
qPyUtils-0.1.9.dist-info/zip-safe
qPyUtils-0.1.9.dist-info/RECORD
