Metadata-Version: 2.1
Name: qPyUtils
Version: 0.1.9
Summary: UNKNOWN
Home-page: https://github.com/koyo922/qPyUtils
Author: Qian Weishuo 
Author-email: qzy922@gmail.com
License: MIT License
Platform: UNKNOWN
Classifier: Development Status :: 2 - Pre-Alpha
Classifier: Environment :: Other Environment
Classifier: Intended Audience :: Developers
Classifier: Programming Language :: Python
Classifier: Programming Language :: Python :: 2.7
Classifier: Programming Language :: Python :: 3.5
Classifier: Programming Language :: Python :: 3.6
Classifier: Topic :: Software Development :: Libraries :: Python Modules
Requires-Dist: six
Requires-Dist: pathlib
Requires-Dist: numpy
Requires-Dist: pandas
Requires-Dist: pyfunctional
Requires-Dist: fn
Requires-Dist: tqdm
Requires-Dist: typing
Requires-Dist: dirtyjson
Requires-Dist: filelike
Requires-Dist: mockito
Requires-Dist: tornado
Requires-Dist: requests
Requires-Dist: docopt
Requires-Dist: chainmap; python_version < "3"
Requires-Dist: futures; python_version < "3"
